[{"maxdelay":20,"S_time":1446400190,"K_time":1446400191,"ip":"::1","ping":7,"start_at":1446396834,"timer":5007,"id":4,"index":"kiosk4","name":"Lobby Kiosk 3","template":"Kiosk1080.php","stamp":1446396834,"status":"undefined"},{"maxdelay":5,"S_time":1446175773,"K_time":1446175774,"ip":"::1","ping":7,"start_at":1446175669,"timer":4999,"id":6,"index":"kiosk6","name":"Kiosk hallway 2","template":"Kiosk1080.php","status":"undefined","stamp":1446175668},{"maxdelay":500,"S_time":0,"K_time":0,"ip":"","ping":0,"start_at":0,"timer":15000,"id":7,"index":"mob0","name":"Mobile","template":"KioskMobile.php?settings=settings"}]